omnisdk/__init__.py
omnisdk/api_endpoint.py
omnisdk/base_client.py
omnisdk/exceptions.py
omnisdk/omnitron/__init__.py
omnisdk/omnitron/client.py
omnisdk/omnitron/endpoints.py
omnisdk/omnitron/models.py
omnisdk-0.0.103.dist-info/METADATA
omnisdk-0.0.103.dist-info/WHEEL
omnisdk-0.0.103.dist-info/top_level.txt
omnisdk-0.0.103.dist-info/RECORD
