Metadata-Version: 2.1
Name: omnisdk
Version: 0.0.103
Summary: SDK for Omni Api
Home-page: https://bitbucket.org/akinonteam/omnisdk
Author: akinonteam
Classifier: Development Status :: 5 - Production/Stable
Requires-Python: >=3.5
Requires-Dist: requests
Requires-Dist: backoff
